{
  "last_update": 1774630507821,
  "rates": {
    "KRW": 1,
    "AED": 0.00244,
    "AFN": 0.0419,
    "ALL": 0.0552,
    "AMD": 0.25,
    "ANG": 0.00119,
    "AOA": 0.624,
    "ARS": 0.964,
    "AUD": 0.00096,
    "AWG": 0.00119,
    "AZN": 0.00113,
    "BAM": 0.00112,
    "BBD": 0.00133,
    "BDT": 0.0814,
    "BGN": 0.00112,
    "BHD": 0.00025,
    "BIF": 1.97,
    "BMD": 0.000664,
    "BND": 0.000853,
    "BOB": 0.0046,
    "BRL": 0.00347,
    "BSD": 0.000664,
    "BTN": 0.0626,
    "BWP": 0.00919,
    "BYN": 0.00199,
    "BZD": 0.00133,
    "CAD": 0.000919,
    "CDF": 1.54,
    "CHF": 0.000527,
    "CLF": 0.000015,
    "CLP": 0.609,
    "CNH": 0.00459,
    "CNY": 0.00459,
    "COP": 2.46,
    "CRC": 0.309,
    "CUP": 0.0159,
    "CVE": 0.0634,
    "CZK": 0.0141,
    "DJF": 0.118,
    "DKK": 0.00429,
    "DOP": 0.0401,
    "DZD": 0.0881,
    "EGP": 0.035,
    "ERN": 0.00995,
    "ETB": 0.104,
    "EUR": 0.000575,
    "FJD": 0.00149,
    "FKP": 0.000498,
    "FOK": 0.00429,
    "GBP": 0.000498,
    "GEL": 0.00179,
    "GGP": 0.000498,
    "GHS": 0.00731,
    "GIP": 0.000498,
    "GMD": 0.0492,
    "GNF": 5.82,
    "GTQ": 0.00508,
    "GYD": 0.138,
    "HKD": 0.00519,
    "HNL": 0.0176,
    "HRK": 0.00433,
    "HTG": 0.0869,
    "HUF": 0.223,
    "IDR": 11.22,
    "ILS": 0.00208,
    "IMP": 0.000498,
    "INR": 0.0626,
    "IQD": 0.868,
    "IRR": 508.66,
    "ISK": 0.0824,
    "JEP": 0.000498,
    "JMD": 0.105,
    "JOD": 0.000471,
    "JPY": 0.106,
    "KES": 0.0862,
    "KGS": 0.058,
    "KHR": 2.67,
    "KID": 0.00096,
    "KMF": 0.283,
    "KWD": 0.000202,
    "KYD": 0.000553,
    "KZT": 0.32,
    "LAK": 14.43,
    "LBP": 59.4,
    "LKR": 0.208,
    "LRD": 0.122,
    "LSL": 0.0113,
    "LYD": 0.00422,
    "MAD": 0.00619,
    "MDL": 0.0116,
    "MGA": 2.78,
    "MKD": 0.0353,
    "MMK": 1.39,
    "MNT": 2.38,
    "MOP": 0.00535,
    "MRU": 0.0264,
    "MUR": 0.0312,
    "MVR": 0.0103,
    "MWK": 1.16,
    "MXN": 0.0118,
    "MYR": 0.00265,
    "MZN": 0.0423,
    "NAD": 0.0113,
    "NGN": 0.918,
    "NIO": 0.0245,
    "NOK": 0.00642,
    "NPR": 0.1,
    "NZD": 0.00115,
    "OMR": 0.000255,
    "PAB": 0.000664,
    "PEN": 0.0023,
    "PGK": 0.00287,
    "PHP": 0.04,
    "PKR": 0.186,
    "PLN": 0.00246,
    "PYG": 4.34,
    "QAR": 0.00242,
    "RON": 0.00293,
    "RSD": 0.0675,
    "RUB": 0.0541,
    "RWF": 0.967,
    "SAR": 0.00249,
    "SBD": 0.00532,
    "SCR": 0.00962,
    "SDG": 0.296,
    "SEK": 0.00624,
    "SGD": 0.000853,
    "SHP": 0.000498,
    "SLE": 0.0163,
    "SLL": 16.33,
    "SOS": 0.378,
    "SRD": 0.025,
    "SSP": 3.05,
    "STN": 0.0141,
    "SYP": 0.0746,
    "SZL": 0.0113,
    "THB": 0.0218,
    "TJS": 0.00632,
    "TMT": 0.00233,
    "TND": 0.00192,
    "TOP": 0.0016,
    "TRY": 0.0295,
    "TTD": 0.00453,
    "TVD": 0.00096,
    "TWD": 0.0212,
    "TZS": 1.72,
    "UAH": 0.0292,
    "UGX": 2.46,
    "USD": 0.000664,
    "UYU": 0.027,
    "UZS": 8.1,
    "VES": 0.311,
    "VND": 17.45,
    "VUV": 0.0796,
    "WST": 0.00182,
    "XAF": 0.377,
    "XCD": 0.00179,
    "XCG": 0.00119,
    "XDR": 0.000489,
    "XOF": 0.377,
    "XPF": 0.0686,
    "YER": 0.158,
    "ZAR": 0.0113,
    "ZMW": 0.0124,
    "ZWG": 0.0168,
    "ZWL": 0.0168
  }
}